azure/mgmt/fluidrelay/__init__.py
azure/mgmt/fluidrelay/_configuration.py
azure/mgmt/fluidrelay/_fluid_relay_management_client.py
azure/mgmt/fluidrelay/_patch.py
azure/mgmt/fluidrelay/_vendor.py
azure/mgmt/fluidrelay/_version.py
azure/mgmt/fluidrelay/py.typed
azure/mgmt/fluidrelay/aio/__init__.py
azure/mgmt/fluidrelay/aio/_configuration.py
azure/mgmt/fluidrelay/aio/_fluid_relay_management_client.py
azure/mgmt/fluidrelay/aio/_patch.py
azure/mgmt/fluidrelay/aio/operations/__init__.py
azure/mgmt/fluidrelay/aio/operations/_fluid_relay_containers_operations.py
azure/mgmt/fluidrelay/aio/operations/_fluid_relay_operations_operations.py
azure/mgmt/fluidrelay/aio/operations/_fluid_relay_servers_operations.py
azure/mgmt/fluidrelay/aio/operations/_patch.py
azure/mgmt/fluidrelay/models/__init__.py
azure/mgmt/fluidrelay/models/_fluid_relay_management_client_enums.py
azure/mgmt/fluidrelay/models/_models_py3.py
azure/mgmt/fluidrelay/models/_patch.py
azure/mgmt/fluidrelay/operations/__init__.py
azure/mgmt/fluidrelay/operations/_fluid_relay_containers_operations.py
azure/mgmt/fluidrelay/operations/_fluid_relay_operations_operations.py
azure/mgmt/fluidrelay/operations/_fluid_relay_servers_operations.py
azure/mgmt/fluidrelay/operations/_patch.py
azure_mgmt_fluidrelay-1.0.0.dist-info/LICENSE
azure_mgmt_fluidrelay-1.0.0.dist-info/METADATA
azure_mgmt_fluidrelay-1.0.0.dist-info/WHEEL
azure_mgmt_fluidrelay-1.0.0.dist-info/top_level.txt
azure_mgmt_fluidrelay-1.0.0.dist-info/RECORD
